django_selecmat-0.0.1.dist-info/METADATA
django_selecmat-0.0.1.dist-info/RECORD
django_selecmat-0.0.1.dist-info/WHEEL
django_selecmat-0.0.1.dist-info/top_level.txt
selecmat/__init__.py
selecmat/config.py
selecmat/meta.py
selecmat/templates/selecmat/attrs.html
selecmat/templates/selecmat/field.html
selecmat/templates/selecmat/form.html
selecmat/templates/selecmat/formset.html
selecmat/templatetags/__init__.py
selecmat/templatetags/selecmat.py
