Metadata-Version: 2.1
Name: django-selecmat
Version: 0.0.1
Summary: A simple Django form template tag to work with MaterializeCSS and Selectize.js
Home-page: https://github.com/dwjorgeb/django-selecmat
Author: Jorge Batista
Author-email: jorge.batista@route.technology
License: MIT
Platform: UNKNOWN
Classifier: Programming Language :: Python
Classifier: Development Status :: 4 - Beta
Classifier: Framework :: Django
Classifier: Intended Audience :: Developers
Classifier: License :: OSI Approved :: MIT License
Classifier: Natural Language :: English
Classifier: Operating System :: OS Independent
Classifier: Programming Language :: Python :: 3.6
